[
    {
        "text": "地震",
        "value": 158.2730993764142
    },
    {
        "text": "新聞",
        "value": 87.02817918619006
    },
    {
        "text": "直播",
        "value": 39.415196928831364
    },
    {
        "text": "台灣",
        "value": 33.72205359994376
    },
    {
        "text": "東森",
        "value": 26.852736038328672
    },
    {
        "text": "新聞直播",
        "value": 24.0
    },
    {
        "text": "news",
        "value": 22.5
    },
    {
        "text": "規模",
        "value": 20.80761721546087
    },
    {
        "text": "強震",
        "value": 19.669992061102466
    },
    {
        "text": "國際",
        "value": 18.281936256945944
    },
    {
        "text": "LIVE",
        "value": 17.5
    },
    {
        "text": "NEWS",
        "value": 17.5
    },
    {
        "text": "Taiwan",
        "value": 17.0
    },
    {
        "text": "台東",
        "value": 16.873067692164895
    },
    {
        "text": "東森新聞",
        "value": 16.5
    },
    {
        "text": "东森",
        "value": 15.5
    },
    {
        "text": "东森新闻",
        "value": 15.5
    },
    {
        "text": "發生",
        "value": 15.456854312729002
    },
    {
        "text": "EBC",
        "value": 14.0
    },
    {
        "text": "Ch51",
        "value": 14.0
    },
    {
        "text": "ㄉㄨㄥ森新聞",
        "value": 14.0
    },
    {
        "text": "東森直播",
        "value": 14.0
    },
    {
        "text": "東森新聞直播",
        "value": 14.0
    },
    {
        "text": "直播新聞",
        "value": 14.0
    },
    {
        "text": "ㄒㄧㄣ新聞直播",
        "value": 14.0
    },
    {
        "text": "東森新聞台",
        "value": 14.0
    },
    {
        "text": "51新聞",
        "value": 14.0
    },
    {
        "text": "#新聞直播",
        "value": 14.0
    },
    {
        "text": "新闻",
        "value": 14.0
    },
    {
        "text": "直播新聞台",
        "value": 14.0
    },
    {
        "text": "東森新聞ch51",
        "value": 14.0
    },
    {
        "text": "線上新聞",
        "value": 14.0
    },
    {
        "text": "花蓮",
        "value": 12.920612479158619
    },
    {
        "text": "News",
        "value": 11.5
    },
    {
        "text": "taiwan",
        "value": 11.0
    },
    {
        "text": "氣象",
        "value": 10.795902122212752
    },
    {
        "text": "中國",
        "value": 10.70027426281052
    },
    {
        "text": "時事",
        "value": 10.589945466941863
    },
    {
        "text": "斷層",
        "value": 10.091892170426384
    },
    {
        "text": "頻道",
        "value": 9.059008081016229
    },
    {
        "text": "即時新聞",
        "value": 9.0
    },
    {
        "text": "pelosi",
        "value": 9.0
    },
    {
        "text": "日本",
        "value": 8.593480288737116
    },
    {
        "text": "政治",
        "value": 8.5
    },
    {
        "text": "十點不一樣",
        "value": 8.0
    },
    {
        "text": "新冠肺炎",
        "value": 8.0
    },
    {
        "text": "基輔",
        "value": 8.0
    },
    {
        "text": "聯合國",
        "value": 8.0
    },
    {
        "text": "北約",
        "value": 8.0
    },
    {
        "text": "澤倫斯基",
        "value": 8.0
    },
    {
        "text": "最新",
        "value": 7.5
    }
]